{
    "data": [
    {
        "id": "1",
        "name": "style1",
        "description": "This is Style One",
        "image": "./imgteengirl/teenagegirl-style1.jpg"
    },
    {
        "id": "2",
        "name": "style2",
        "description": "This is Style Two",
        "image": "imgteengirl/teenagegirl-style2.jpg"
    },
    {
        "id": "3",
        "name": "style3",
        "description": "This is Style Three",
        "image": "imgteengirl/teenagegirl-style3.jpg"
    },
    {
        "id": "4",
        "name": "style4",
        "description": "This is Style Four",
        "image": "imgteengirl/teenagegirl-style4.jpg"
    },
    {
        "id": "5",
        "name": "style5",
        "description": "This is Style Five",
        "image": "imgteengirl/teenagegirl-style5.jpg"
    },
    {
        "id": "6",
        "name": "style6",
        "description": "This is Style Six",
        "image": "imgteengirl/teenagegirl-style6.jpg"
    },
    {
        "id": "7",
        "name": "style7",
        "description": "This is Style Seven",
        "image": "imgteengirl/teenagegirl-style7.jpg"
    },
    {
        "id": "8",
        "name": "style8",
        "description": "This is Style Eight",
        "image": "imgteengirl/teenagegirl-style8.jpg"
    },
    {
        "id": "9",
        "name": "style9",
        "description": "This is Style Nine",
        "image": "imgteengirl/teenagegirl-style9.jpg"
    },
    {
        "id": "10",
        "name": "style10",
        "description": "This is Style Ten",
        "image": "imgteengirl/teenagegirl-style10.jpg"
    },
    {
        "id": "11",
        "name": "style11",
        "description": "This is Style Eleven",
        "image": "imgteengirl/teenagegirl-style11.jpg"
    },
    {
        "id": "12",
        "name": "style12",
        "description": "This is Style Twelve",
        "image": "imgteengirl/teenagegirl-style12.jpg"
    },
    {
        "id": "13",
        "name": "style13",
        "description": "This is Style Thirteen",
        "image": "imgteengirl/teenagegirl-style13.jpg"
    },
    {
        "id": "14",
        "name": "style14",
        "description": "This is Style Fourteen",
        "image": "imgteengirl/teenagegirl-style14.jpg"
    },
    {
        "id": "15",
        "name": "style15",
        "description": "This is Style Fifteen",
        "image": "imgteengirl/teenagegirl-style15.jpg"
    },
    {
        "id": "16",
        "name": "style16",
        "description": "This is Style Sixteen",
        "image": "imgteengirl/teenagegirl-style16.jpg"
    },
    {
        "id": "17",
        "name": "style17",
        "description": "This is Style Seventeen",
        "image": "imgteengirl/teenagegirl-style17.jpg"
    },
    {
        "id": "18",
        "name": "style18",
        "description": "This is Style Eighteen",
        "image": "imgteengirl/teenagegirl-style18.jpg"
    },
    {
        "id": "19",
        "name": "style19",
        "description": "This is Style Nineteen",
        "image": "imgteengirl/teenagegirl-style19.jpg"
    },
    {
        "id": "20",
        "name": "style20",
        "description": "This is Style Twenty",
        "image": "imgteengirl/teenagegirl-style20.jpg"
    },
    {
        "id": "21",

        "name": "style21",
        "description": "This is Style TwentyOne",
        "image": "imgteengirl/teenagegirl-style21.jpg"
    },
    {
        "id": "22",
        "name": "style22",
        "description": "This is Style TwentyTwo",
        "image": "imgteengirl/teenagegirl-style22.jpg"
    },
    {
        "id": "23",
        "name": "style23",
        "description": "This is Style TwentyThree",
        "image": "imgteengirl/teenagegirl-style23.jpg"
    },  
    {
        "id": "24",
        "name": "style24",
        "description": "This is Style TwentyFour",
        "image": "imgteengirl/teenagegirl-style24.jpg"
    },  
    {
        "id": "25",
        "name": "style25",
        "description": "This is Style TwentyFive",
        "image": "imgteengirl/teenagegirl-style25.jpg"
    },  
    {
        "id": "26",
        "name": "style26",
        "description": "This is Style TwentySix",
        "image": "imgteengirl/teenagegirl-style26.jpg"
    },  
    {
        "id": "27",
        "name": "style27",
        "description": "This is Style TwentySeven",
        "image": "imgteengirl/teenagegirl-style27.jpg"
    },
    {
        "id": "28",
        "name": "style28",
        "description": "This is Style TwentyEight",
        "image": "imgteengirl/teenagegirl-style28.jpg"
    },
    {
        "id": "29",
        "name": "style29",
        "description": "This is Style TwentyNine",
        "image": "imgteengirl/teenagegirl-style29.jpg"
    },
    {
        "id": "30",
        "name": "style30",
        "description": "This is Style Thirty",
        "image": "imgteengirl/teenagegirl-style30.jpg"
},
{
        "id": "31",
        "name": "style31",
        "description": "This is Style ThirtyOne",
        "image": "imgteengirl/teenagegirl-style31.jpg"
},
    {
        "id": "32",
        "name": "style32",
        "description": "This is Style ThirtyTwo",
        "image": "imgteengirl/teenagegirl-style32.jpg"
    },
    {
        "id": "33",
        "name": "style33",
        "description": "This is Style ThirtyThree",
        "image": "imgteengirl/teenagegirl-style33.jpg"
    },
    {
        "id": "34",
        "name": "style34",
        "description": "This is Style ThirtyFour",
        "image": "imgteengirl/teenagegirl-style34.jpg"
    },
    {
        "id": "35",
        "name": "style35",
        "description": "This is Style ThirtyFive",
        "image": "imgteengirl/teenagegirl-style35.jpg"
    },
    {
        "id": "36",
        "name": "style36",
        "description": "This is Style ThirtySix",
        "image": "imgteengirl/teenagegirl-style36.jpg"
    },
    {
        "id": "37",
        "name": "style37",
        "description": "This is Style ThirtySeven",
        "image": "imgteengirl/teenagegirl-style37.jpg"
    },
    {
        "id": "38",
        "name": "style38",
        "description": "This is Style ThirtyEight",
        "image": "imgteengirl/teenagegirl-style38.jpg"
    },{
        "id": "39",
        "name": "style39",
        "description": "This is Style ThirtyNine",
        "image": "imgteengirl/teenagegirl-style39.jpg"
    },
    {
        "id": "40",
        "name": "style40",
        "description": "This is Style Fourty",
        "image": "imgteengirl/teenagegirl-style40.jpg"
    },
    {
        "id": "41",
        "name": "style41",
        "description": "This is Style FourtyOne",
        "image": "imgteengirl/teenagegirl-style41.jpg"
    },
    {
        "id": "42",
        "name": "style42",
        "description": "This is Style FourtyTwo",
        "image": "imgteengirl/teenagegirl-style42.jpg"
    },
    {
        "id": "43",
        "name": "style43",
        "description": "This is Style FourtyThree",
        "image": "imgteengirl/teenagegirl-style43.jpg"
    },
    {
        "id": "44",
        "name": "style44",
        "description": "This is Style FourtyFour",
        "image": "imgteengirl/teenagegirl-style44.jpg"
    },
    {
        "id": "45",
        "name": "style45",
        "description": "This is Style FourtyFive",
        "image": "imgteengirl/teenagegirl-style45.jpg"
    },
    {
        "id": "46",
        "name": "style46",
        "description": "This is Style FourtySix",
        "image": "imgteengirl/teenagegirl-style46.jpg"
    },
    {
        "id": "47",
        "name": "style47",
        "description": "This is Style FourtySeven",
        "image": "imgteengirl/teenagegirl-style47.jpg"
    },
    {
        "id": "48",
        "name": "style48",
        "description": "This is Style FourtyEight",
        "image": "imgteengirl/teenagegirl-style48.jpg"
    },
    {
        "id": "49",
        "name": "style49",
        "description": "This is Style FourtyNine",
        "image": "imgteengirl/teenagegirl-style49.jpg"
    },
    {
        "id": "50",
        "name": "style50",
        "description": "This is Style Fifty",
        "image": "imgteengirl/teenagegirl-style50.jpg"
    },
    {
        "id": "51",
        "name": "style51",
        "description": "This is Style FiftyOne",
        "image": "imgteengirl/teenagegirl-style51.jpg"
    },
    {
        "id": "52",
        "name": "style52",
        "description": "This is Style FiftyTwo",
        "image": "imgteengirl/teenagegirl-style52.jpg"
    },
    {
        "id": "53",
        "name": "style53",
        "description": "This is Style FiftyThree",
        "image": "imgteengirl/teenagegirl-style53.jpg"
    },
    {
        "id": "54",
        "name": "style54",
        "description": "This is Style FiftyFour",
        "image": "imgteengirl/teenagegirl-style54.jpg"
    },
    {
        "id": "55",
        "name": "style55",
        "description": "This is Style FiftyFive",
        "image": "imgteengirl/teenagegirl-style55.jpg"
    },
    {
        "id": "56",
        "name": "style56",
        "description": "This is Style FiftySix",
        "image": "imgteengirl/teenagegirl-style56.jpg"
    },
    {
        "id": "57",
        "name": "style57",
        "description": "This is Style FiftySeven",
        "image": "imgteengirl/teenagegirl-style57.jpg"
    },
    {
        "id": "58",
        "name": "style58",
        "description": "This is Style FiftyEight",
        "image": "imgteengirl/teenagegirl-style58.jpg"
    },
    {
        "id": "59",
        "name": "style59",
        "description": "This is Style FiftyNine",
        "image": "imgteengirl/teenagegirl-style59.jpg"
    },
    {
        "id": "60",
        "name": "style60",
        "description": "This is Style Sixty",
        "image": "imgteengirl/teenagegirl-style60.jpg"
    },
    {
        "id": "61",
        "name": "style61",
        "description": "This is Style SixtyOne",
        "image": "imgteengirl/teenagegirl-style61.jpg"
    },
    {
        "id": "62",
        "name": "style62",
        "description": "This is Style SixtyTwo",
        "image": "imgteengirl/teenagegirl-style62.jpg"
    },
    {
        "id": "63",
        "name": "style63",
        "description": "This is Style SixtyThree",
        "image": "imgteengirl/teenagegirl-style63.jpg"
    },
    {
        "id": "64",
        "name": "style64",
        "description": "This is Style SixtyFour",
        "image": "imgteengirl/teenagegirl-style64.jpg"
    },
    {
        "id": "65",
        "name": "style65",
        "description": "This is Style SixtyFive",
        "image": "imgteengirl/teenagegirl-style65.jpg"
    },
    {
        "id": "66",
        "name": "style66",
        "description": "This is Style SixtyXix",
        "image": "imgteengirl/teenagegirl-style66.jpg"
    },
    {
        "id": "67",
        "name": "style67",
        "description": "This is Style SixtySeven",
        "image": "imgteengirl/teenagegirl-style67.jpg"
    },
    {
        "id": "68",
        "name": "style68",
        "description": "This is Style SixtyEight",
        "image": "imgteengirl/teenagegirl-style68.jpg"
    },
    {
        "id": "69",
        "name": "style69",
        "description": "This is Style SixtyNine",
        "image": "imgteengirl/teenagegirl-style69.jpg"
    },
    {
        "id": "70",
        "name": "style70",
        "description": "This is Style Seventy",
        "image": "imgteengirl/teenagegirl-style70.jpg"
    },
    {
        "id": "71",
        "name": "style71",
        "description": "This is Style SeventyOne",
        "image": "imgteengirl/teenagegirl-style71.jpg"
    },
    {
        "id": "72",
        "name": "style72",
        "description": "This is Style SeventyTwo",
        "image": "imgteengirl/teenagegirl-style72.jpg"
    },
    {
        "id": "73",
        "name": "style73",
        "description": "This is Style SeventyThree",
        "image": "imgteengirl/teenagegirl-style73.jpg"
    },
    {
        "id": "74",
        "name": "style74",
        "description": "This is Style SeventyFour",
        "image": "imgteengirl/teenagegirl-style74.jpg"
    },
    {
        "id": "75",
        "name": "style75",
        "description": "This is Style SeventyFive",
        "image": "imgteengirl/teenagegirl-style75.jpg"
    },
    {
        "id": "76",
        "name": "style76",
        "description": "This is Style SeventySix",
        "image": "imgteengirl/teenagegirl-style76.jpg"
    },
    {
        "id": "77",
        "name": "style77",
        "description": "This is Style SeventySeven",
        "image": "imgteengirl/teenagegirl-style77.jpg"
    },
    {
        "id": "78",
        "name": "style78",
        "description": "This is Style SeventyEight",
        "image": "imgteengirl/teenagegirl-style78.jpg"
    },
    {
        "id": "79",
        "name": "style79",
        "description": "This is Style SeventyNine",
        "image": "imgteengirl/teenagegirl-style79.jpg"
    },
    {
        "id": "80",
        "name": "style80",
        "description": "This is Style Eighty",
        "image": "imgteengirl/teenagegirl-style80.jpg"
    },
    {
        "id": "81",
        "name": "style81",
        "description": "This is Style EightyOne",
        "image": "imgteengirl/teenagegirl-style81.jpg"
    },
    {
        "id": "82",
        "name": "style82",
        "description": "This is Style Eighty",
        "image": "imgteengirl/teenagegirl-style82.jpg"
    },
    {
        "id": "83",
        "name": "style83",
        "description": "This is Style Eighty",
        "image": "imgteengirl/teenagegirl-style83.jpg"
    },
    {
        "id": "84",
        "name": "style84",
        "description": "This is Style Eighty",
        "image": "imgteengirl/teenagegirl-style84.jpg"
    },
    {
        "id": "85",
        "name": "style85",
        "description": "This is Style Eighty",
        "image": "imgteengirl/teenagegirl-style85.jpg"
    },
    {
        "id": "86",
        "name": "style86",
        "description": "This is Style EightySix",
        "image": "imgteengirl/teenagegirl-style86.jpg"
    },
    {
        "id": "87",
        "name": "style87",
        "description": "This is Style EightySeven",
        "image": "imgteengirl/teenagegirl-style87.jpg"
    },
    {
        "id": "88",
        "name": "style88",
        "description": "This is Style EightyEight",
        "image": "imgteengirl/teenagegirl-style88.jpg"
    },
    {
        "id": "89",
        "name": "style89",
        "description": "This is Style EightyNine",
        "image": "imgteengirl/teenagegirl-style89.jpg"
    },
    {
        "id": "90",
        "name": "style90",
        "description": "This is Style Ninety",
        "image": "imgteengirl/teenagegirl-style90.jpg"
    },
    {
        "id": "91",
        "name": "style91",
        "description": "This is Style NinetyOne",
        "image": "imgteengirl/teenagegirl-style91.jpg"
    },
    {
        "id": "92",
        "name": "style92",
        "description": "This is Style NinetyTwo",
        "image": "imgteengirl/teenagegirl-style92.jpg"
    },
    {
        "id": "93",
        "name": "style93",
        "description": "This is Style NinetyThree",
        "image": "imgteengirl/teenagegirl-style93.jpg"
    },
    {
        "id": "94",
        "name": "style94",
        "description": "This is Style NinetyFour",
        "image": "imgteengirl/teenagegirl-style94.jpg"
    },
    {
        "id": "95",
        "name": "style95",
        "description": "This is Style NinetyFive",
        "image": "imgteengirl/teenagegirl-style95.jpg"
    },
    {
        "id": "96",
        "name": "style96",
        "description": "This is Style NinetySix",
        "image": "imgteengirl/teenagegirl-style96.jpg"
    },
    {
        "id": "97",
        "name": "style97",
        "description": "This is Style NinetySeven",
        "image": "imgteengirl/teenagegirl-style97.jpg"
    },
    {
        "id": "98",
        "name": "style98",
        "description": "This is Style NinetyEight",
        "image": "imgteengirl/teenagegirl-style98.jpg"
    },
    {
        "id": "99",
        "name": "style99",
        "description": "This is Style NinetyNine",
        "image": "imgteengirl/teenagegirl-style99.jpg"
    },
    {
        "id": "100",
        "name": "style100",
        "description": "This is Style OneHundred",
        "image": "imgteengirl/teenagegirl-style100.jpg"
    },
    {
        "id": "101",
        "name": "style101",
        "description": "This is Style OneHundredOne",
        "image": "imgteengirl/teenagegirl-style101.jpg"
    },
    {
        "id": "102",
        "name": "style102",
        "description": "This is Style OneHundredTwo",
        "image": "imgteengirl/teenagegirl-style102.jpg"
    },
    {
        "id": "103",
        "name": "style103",
        "description": "This is Style OneHundredThree",
        "image": "imgteengirl/teenagegirl-style103.jpg"
    }

]

}